lambdafaker/__init__.py
lambdafaker/aws.py
lambdafaker/awslambda.py
lambdafaker/cli.py
lambdafaker/config.py
lambdafaker/lambdafaker.py
lambdafaker/util.py
lambdafaker-1.0.0.dist-info/LICENSE
lambdafaker-1.0.0.dist-info/METADATA
lambdafaker-1.0.0.dist-info/WHEEL
lambdafaker-1.0.0.dist-info/entry_points.txt
lambdafaker-1.0.0.dist-info/top_level.txt
lambdafaker-1.0.0.dist-info/RECORD
